<members>
  <member name="T:VRC.SDKBase.VRC_Panorama">
    <docURL>???</docURL>
    <incomplete />
    <summary>This is not documented properly yet</summary>
  </member>
  <member name="T:VRC.SDKBase.VRC_Panorama.Layout">
    <docURL>???</docURL>
    <incomplete />
    <summary>This is not documented properly yet</summary>
  </member>
  <member name="T:VRC.SDKBase.VRC_Panorama.PanoSpec">
    <docURL>???</docURL>
    <incomplete />
    <summary>This is not documented properly yet</summary>
  </member>
</members>