<members>
  <member name="T:VRC.SDKBase.VRC_Trigger">
    <docURL>???</docURL>
    <incomplete />
    <summary>This is not documented properly yet</summary>
  </member>
  <member name="T:VRC.SDKBase.VRC_TriggerColliderEventTrigger">
    <docURL>???</docURL>
    <incomplete />
    <summary>This is not documented properly yet</summary>
  </member>
  <member name="T:VRC.SDKBase.VRC_Trigger.CustomTriggerTarget">
    <docURL>???</docURL>
    <incomplete />
    <summary>This is not documented properly yet</summary>
  </member>
  <member name="T:VRC.SDKBase.VRC_Trigger.TriggerType">
    <docURL>???</docURL>
    <incomplete />
    <summary>This is not documented properly yet</summary>
  </member>
  <member name="T:VRC.SDKBase.VRC_Trigger.EditorTriggerLineMode">
    <docURL>???</docURL>
    <incomplete />
    <summary>This is not documented properly yet</summary>
  </member>
  <member name="T:VRC.SDKBase.VRC_Trigger.TypeCollections">
    <docURL>???</docURL>
    <incomplete />
    <summary>This is not documented properly yet</summary>
  </member>
  <member name="T:VRC.SDKBase.VRC_Trigger.DataStorageShadow">
    <docURL>???</docURL>
    <incomplete />
    <summary>This is not documented properly yet</summary>
  </member>
  <member name="T:VRC.SDKBase.VRC_Trigger.TriggerEvent">
    <docURL>???</docURL>
    <incomplete />
    <summary>This is not documented properly yet</summary>
  </member>
</members>