<members>
  <member name="F:VRC.SDK3.Image.VRCImageDownloader.ImageDownloader.ImageError.Unknown">
    <docURL>???</docURL>
    <incomplete />
    <summary>This is not documented properly yet</summary>
  </member>
  <member name="F:VRC.SDK3.Image.VRCImageDownloader.ImageDownloader.ImageError.MaximumDimensionExceeded">
    <docURL>???</docURL>
    <incomplete />
    <summary>This is not documented properly yet</summary>
  </member>
  <member name="F:VRC.SDK3.Image.VRCImageDownloader.ImageDownloader.ImageError.LoadFailure">
    <docURL>???</docURL>
    <incomplete />
    <summary>This is not documented properly yet</summary>
  </member>
  <member name="F:VRC.SDK3.Image.VRCImageDownloader.ImageDownloader.ImageError.DecodeFailure">
    <docURL>???</docURL>
    <incomplete />
    <summary>This is not documented properly yet</summary>
  </member>
  <member name="F:VRC.SDK3.Image.VRCImageDownloader.ImageDownloader.ImageError.IoError">
    <docURL>???</docURL>
    <incomplete />
    <summary>This is not documented properly yet</summary>
  </member>
  <member name="F:VRC.SDK3.Image.VRCImageDownloader.ImageDownloader.ImageError.LimitsExceeded">
    <docURL>???</docURL>
    <incomplete />
    <summary>This is not documented properly yet</summary>
  </member>
  <member name="F:VRC.SDK3.Image.VRCImageDownloader.ImageDownloader.ImageError.UnsupportedOperation">
    <docURL>???</docURL>
    <incomplete />
    <summary>This is not documented properly yet</summary>
  </member>
  <member name="F:VRC.SDK3.Image.VRCImageDownloader.ImageDownloader.ImageError.UnknownFormat">
    <docURL>???</docURL>
    <incomplete />
    <summary>This is not documented properly yet</summary>
  </member>
  <member name="F:VRC.SDK3.Image.VRCImageDownloader.ImageDownloader.ImageError.OutputBufferTooSmall">
    <docURL>???</docURL>
    <incomplete />
    <summary>This is not documented properly yet</summary>
  </member>
  <member name="F:VRC.SDK3.Image.VRCImageDownloader.ImageDownloader.ImageError.Panic">
    <docURL>???</docURL>
    <incomplete />
    <summary>This is not documented properly yet</summary>
  </member>
  <member name="F:VRC.SDK3.Image.VRCImageDownloader.ImageDownloader.ImageError.UnsupportedLimits">
    <docURL>???</docURL>
    <incomplete />
    <summary>This is not documented properly yet</summary>
  </member>
  <member name="F:VRC.SDK3.Image.VRCImageDownloader.ImageDownloader.ImageError.MemoryLimitExceeded">
    <docURL>???</docURL>
    <incomplete />
    <summary>This is not documented properly yet</summary>
  </member>
  <member name="F:VRC.SDK3.Image.VRCImageDownloader.ImageDownloader.ImageError.BadDecoderParameters">
    <docURL>???</docURL>
    <incomplete />
    <summary>This is not documented properly yet</summary>
  </member>
  <member name="F:VRC.SDK3.Image.VRCImageDownloader.ImageDownloader.ImageFormat.Unknown">
    <docURL>???</docURL>
    <incomplete />
    <summary>This is not documented properly yet</summary>
  </member>
  <member name="F:VRC.SDK3.Image.VRCImageDownloader.ImageDownloader.ImageFormat.R8">
    <docURL>???</docURL>
    <incomplete />
    <summary>This is not documented properly yet</summary>
  </member>
  <member name="F:VRC.SDK3.Image.VRCImageDownloader.ImageDownloader.ImageFormat.RG16">
    <docURL>???</docURL>
    <incomplete />
    <summary>This is not documented properly yet</summary>
  </member>
  <member name="F:VRC.SDK3.Image.VRCImageDownloader.ImageDownloader.ImageFormat.RGB24">
    <docURL>???</docURL>
    <incomplete />
    <summary>This is not documented properly yet</summary>
  </member>
  <member name="F:VRC.SDK3.Image.VRCImageDownloader.ImageDownloader.ImageFormat.RGBA32">
    <docURL>???</docURL>
    <incomplete />
    <summary>This is not documented properly yet</summary>
  </member>
  <member name="F:VRC.SDK3.Image.VRCImageDownloader.ImageDownloader.ImageFormat.R16">
    <docURL>???</docURL>
    <incomplete />
    <summary>This is not documented properly yet</summary>
  </member>
  <member name="F:VRC.SDK3.Image.VRCImageDownloader.ImageDownloader.ImageFormat.RG32">
    <docURL>???</docURL>
    <incomplete />
    <summary>This is not documented properly yet</summary>
  </member>
  <member name="F:VRC.SDK3.Image.VRCImageDownloader.ImageDownloader.ImageFormat.RGB48">
    <docURL>???</docURL>
    <incomplete />
    <summary>This is not documented properly yet</summary>
  </member>
  <member name="F:VRC.SDK3.Image.VRCImageDownloader.ImageDownloader.ImageFormat.RGBA64">
    <docURL>???</docURL>
    <incomplete />
    <summary>This is not documented properly yet</summary>
  </member>
  <member name="F:VRC.SDK3.Image.VRCImageDownloader.ImageDownloader.ImageFormat.RGBAFloat">
    <docURL>???</docURL>
    <incomplete />
    <summary>This is not documented properly yet</summary>
  </member>
  <member name="F:VRC.SDK3.Image.VRCImageDownloader.ImageDownloader.ImageInfo.width">
    <docURL>???</docURL>
    <incomplete />
    <summary>This is not documented properly yet</summary>
  </member>
  <member name="F:VRC.SDK3.Image.VRCImageDownloader.ImageDownloader.ImageInfo.height">
    <docURL>???</docURL>
    <incomplete />
    <summary>This is not documented properly yet</summary>
  </member>
  <member name="F:VRC.SDK3.Image.VRCImageDownloader.ImageDownloader.ImageInfo.format">
    <docURL>???</docURL>
    <incomplete />
    <summary>This is not documented properly yet</summary>
  </member>
  <member name="F:VRC.SDK3.Image.VRCImageDownloader.ImageDownloader.ImageResult.success">
    <docURL>???</docURL>
    <incomplete />
    <summary>This is not documented properly yet</summary>
  </member>
  <member name="F:VRC.SDK3.Image.VRCImageDownloader.ImageDownloader.ImageResult.info">
    <docURL>???</docURL>
    <incomplete />
    <summary>This is not documented properly yet</summary>
  </member>
  <member name="F:VRC.SDK3.Image.VRCImageDownloader.ImageDownloader.ImageResult.error">
    <docURL>???</docURL>
    <incomplete />
    <summary>This is not documented properly yet</summary>
  </member>
  <member name="F:VRC.SDK3.Image.VRCImageDownloader.ImageDownloader.ImageLoadSettingsFlags.None">
    <docURL>???</docURL>
    <incomplete />
    <summary>This is not documented properly yet</summary>
  </member>
  <member name="F:VRC.SDK3.Image.VRCImageDownloader.ImageDownloader.ImageLoadSettingsFlags.LimitAllocation">
    <docURL>???</docURL>
    <incomplete />
    <summary>This is not documented properly yet</summary>
  </member>
  <member name="F:VRC.SDK3.Image.VRCImageDownloader.ImageDownloader.ImageLoadSettingsFlags.LimitResolution">
    <docURL>???</docURL>
    <incomplete />
    <summary>This is not documented properly yet</summary>
  </member>
  <member name="F:VRC.SDK3.Image.VRCImageDownloader.ImageDownloader.ImageLoadSettingsFlags.VerticalFlip">
    <docURL>???</docURL>
    <incomplete />
    <summary>This is not documented properly yet</summary>
  </member>
  <member name="F:VRC.SDK3.Image.VRCImageDownloader.ImageDownloader.ImageLoadSettingsFlags.OverrideOutputFormat">
    <docURL>???</docURL>
    <incomplete />
    <summary>This is not documented properly yet</summary>
  </member>
  <member name="F:VRC.SDK3.Image.VRCImageDownloader.ImageDownloader.ImageLoadSettingsFlags.ResizeOutput">
    <docURL>???</docURL>
    <incomplete />
    <summary>This is not documented properly yet</summary>
  </member>
  <member name="F:VRC.SDK3.Image.VRCImageDownloader.ImageDownloader.ImageLoadSettingsFlags.FastResize">
    <docURL>???</docURL>
    <incomplete />
    <summary>This is not documented properly yet</summary>
  </member>
  <member name="F:VRC.SDK3.Image.VRCImageDownloader.ImageDownloader.ImageLoadSettingsFlags.GenerateMipMaps">
    <docURL>???</docURL>
    <incomplete />
    <summary>This is not documented properly yet</summary>
  </member>
  <member name="P:VRC.SDK3.Image.VRCImageDownloader.StartDownload">
    <docURL>???</docURL>
    <incomplete />
    <summary>This is not documented properly yet</summary>
  </member>
  <member name="P:VRC.SDK3.Image.VRCImageDownloader.HasAnyQueuedDownloads">
    <docURL>???</docURL>
    <incomplete />
    <summary>This is not documented properly yet</summary>
  </member>
  <member name="P:VRC.SDK3.Image.VRCImageDownloader.ImageDownloader.State">
    <docURL>???</docURL>
    <incomplete />
    <summary>This is not documented properly yet</summary>
  </member>
  <member name="P:VRC.SDK3.Image.VRCImageDownloader.ImageDownloader.Error">
    <docURL>???</docURL>
    <incomplete />
    <summary>This is not documented properly yet</summary>
  </member>
  <member name="P:VRC.SDK3.Image.VRCImageDownloader.ImageDownloader.ErrorMessage">
    <docURL>???</docURL>
    <incomplete />
    <summary>This is not documented properly yet</summary>
  </member>
  <member name="P:VRC.SDK3.Image.VRCImageDownloader.ImageDownloader.Result">
    <docURL>???</docURL>
    <incomplete />
    <summary>This is not documented properly yet</summary>
  </member>
  <member name="P:VRC.SDK3.Image.VRCImageDownloader.ImageDownloader.SizeInMemoryBytes">
    <docURL>???</docURL>
    <incomplete />
    <summary>This is not documented properly yet</summary>
  </member>
  <member name="P:VRC.SDK3.Image.VRCImageDownloader.ImageDownloader.Progress">
    <docURL>???</docURL>
    <incomplete />
    <summary>This is not documented properly yet</summary>
  </member>
  <member name="P:VRC.SDK3.Image.VRCImageDownloader.ImageDownloader.Url">
    <docURL>???</docURL>
    <incomplete />
    <summary>This is not documented properly yet</summary>
  </member>
  <member name="P:VRC.SDK3.Image.VRCImageDownloader.ImageDownloader.Material">
    <docURL>???</docURL>
    <incomplete />
    <summary>This is not documented properly yet</summary>
  </member>
  <member name="P:VRC.SDK3.Image.VRCImageDownloader.ImageDownloader.UdonBehaviour">
    <docURL>???</docURL>
    <incomplete />
    <summary>This is not documented properly yet</summary>
  </member>
  <member name="P:VRC.SDK3.Image.VRCImageDownloader.ImageDownloader.TextureInfo">
    <docURL>???</docURL>
    <incomplete />
    <summary>This is not documented properly yet</summary>
  </member>
  <member name="M:VRC.SDK3.Image.VRCImageDownloader.DownloadImage(VRC.SDKBase.VRCUrl,UnityEngine.Material,VRC.Udon.Common.Interfaces.IUdonEventReceiver,VRC.SDK3.Image.TextureInfo)">
    <docURL>???</docURL>
    <incomplete />
    <summary>This is not documented properly yet</summary>
    <param name="url">???</param>
    <param name="material">???</param>
    <param name="udonBehaviour">???</param>
    <param name="textureInfo">???</param>
  </member>
  <member name="M:VRC.SDK3.Image.VRCImageDownloader.Dispose">
    <docURL>???</docURL>
    <incomplete />
    <summary>This is not documented properly yet</summary>
  </member>
  <member name="M:VRC.SDK3.Image.VRCImageDownloader.AddImageDownloadToQueue(VRC.SDK3.Image.IVRCImageDownload)">
    <docURL>???</docURL>
    <incomplete />
    <summary>This is not documented properly yet</summary>
    <param name="imageDownload">???</param>
  </member>
  <member name="M:VRC.SDK3.Image.VRCImageDownloader.RemoveImageDownloadFromQueue(VRC.SDK3.Image.IVRCImageDownload)">
    <docURL>???</docURL>
    <incomplete />
    <summary>This is not documented properly yet</summary>
    <param name="imageDownload">???</param>
  </member>
  <member name="M:VRC.SDK3.Image.VRCImageDownloader.ClearQueue">
    <docURL>???</docURL>
    <incomplete />
    <summary>This is not documented properly yet</summary>
  </member>
  <member name="M:VRC.SDK3.Image.VRCImageDownloader..ctor">
    <docURL>???</docURL>
    <incomplete />
    <summary>This is not documented properly yet</summary>
  </member>
  <member name="M:VRC.SDK3.Image.VRCImageDownloader.ImageDownloader.DownloadImage(VRC.SDKBase.VRCUrl,UnityEngine.Material,VRC.Udon.Common.Interfaces.IUdonEventReceiver,VRC.SDK3.Image.TextureInfo)">
    <docURL>???</docURL>
    <incomplete />
    <summary>This is not documented properly yet</summary>
    <param name="url">???</param>
    <param name="material">???</param>
    <param name="udonBehaviour">???</param>
    <param name="textureInfo">???</param>
  </member>
  <member name="M:VRC.SDK3.Image.VRCImageDownloader.ImageDownloader..ctor(VRC.SDKBase.VRCUrl,UnityEngine.Material,VRC.Udon.Common.Interfaces.IUdonEventReceiver,VRC.SDK3.Image.TextureInfo)">
    <docURL>???</docURL>
    <incomplete />
    <summary>This is not documented properly yet</summary>
    <param name="url">???</param>
    <param name="material">???</param>
    <param name="udonBehaviour">???</param>
    <param name="textureInfo">???</param>
  </member>
  <member name="M:VRC.SDK3.Image.VRCImageDownloader.ImageDownloader.StartDownload">
    <docURL>???</docURL>
    <incomplete />
    <summary>This is not documented properly yet</summary>
  </member>
  <member name="M:VRC.SDK3.Image.VRCImageDownloader.ImageDownloader.Dispose">
    <docURL>???</docURL>
    <incomplete />
    <summary>This is not documented properly yet</summary>
  </member>
  <member name="M:VRC.SDK3.Image.VRCImageDownloader.ImageDownloader.CancelDownload">
    <docURL>???</docURL>
    <incomplete />
    <summary>This is not documented properly yet</summary>
  </member>
  <member name="M:VRC.SDK3.Image.VRCImageDownloader.ImageDownloader.ImageInfo..ctor">
    <docURL>???</docURL>
    <incomplete />
    <summary>This is not documented properly yet</summary>
  </member>
  <member name="M:VRC.SDK3.Image.VRCImageDownloader.ImageDownloader.ImageResult..ctor">
    <docURL>???</docURL>
    <incomplete />
    <summary>This is not documented properly yet</summary>
  </member>
  <member name="M:VRC.SDK3.Image.VRCImageDownloader.ImageDownloader.ImageLoadSettings.GetAllocationLimit">
    <docURL>???</docURL>
    <incomplete />
    <summary>This is not documented properly yet</summary>
  </member>
  <member name="M:VRC.SDK3.Image.VRCImageDownloader.ImageDownloader.ImageLoadSettings.SetAllocationLimit(System.Nullable)">
    <docURL>???</docURL>
    <incomplete />
    <summary>This is not documented properly yet</summary>
    <param name="allocationLimit">???</param>
  </member>
  <member name="M:VRC.SDK3.Image.VRCImageDownloader.ImageDownloader.ImageLoadSettings.GetResolutionLimit">
    <docURL>???</docURL>
    <incomplete />
    <summary>This is not documented properly yet</summary>
  </member>
  <member name="M:VRC.SDK3.Image.VRCImageDownloader.ImageDownloader.ImageLoadSettings.SetResolutionLimit(System.Nullable)">
    <docURL>???</docURL>
    <incomplete />
    <summary>This is not documented properly yet</summary>
    <param name="resolutionLimit">???</param>
  </member>
  <member name="M:VRC.SDK3.Image.VRCImageDownloader.ImageDownloader.ImageLoadSettings.GetVerticalFlip">
    <docURL>???</docURL>
    <incomplete />
    <summary>This is not documented properly yet</summary>
  </member>
  <member name="M:VRC.SDK3.Image.VRCImageDownloader.ImageDownloader.ImageLoadSettings.SetVerticalFlip(System.Boolean)">
    <docURL>???</docURL>
    <incomplete />
    <summary>This is not documented properly yet</summary>
    <param name="flip">???</param>
  </member>
  <member name="M:VRC.SDK3.Image.VRCImageDownloader.ImageDownloader.ImageLoadSettings.GetResizeResolution">
    <docURL>???</docURL>
    <incomplete />
    <summary>This is not documented properly yet</summary>
  </member>
  <member name="M:VRC.SDK3.Image.VRCImageDownloader.ImageDownloader.ImageLoadSettings.SetResizeResolution(System.Nullable)">
    <docURL>???</docURL>
    <incomplete />
    <summary>This is not documented properly yet</summary>
    <param name="targetResolution">???</param>
  </member>
  <member name="M:VRC.SDK3.Image.VRCImageDownloader.ImageDownloader.ImageLoadSettings.SetFastResize(System.Boolean)">
    <docURL>???</docURL>
    <incomplete />
    <summary>This is not documented properly yet</summary>
    <param name="fast">???</param>
  </member>
  <member name="M:VRC.SDK3.Image.VRCImageDownloader.ImageDownloader.ImageLoadSettings.GetFastResize">
    <docURL>???</docURL>
    <incomplete />
    <summary>This is not documented properly yet</summary>
  </member>
  <member name="M:VRC.SDK3.Image.VRCImageDownloader.ImageDownloader.ImageLoadSettings.GetOutputFormatOverride">
    <docURL>???</docURL>
    <incomplete />
    <summary>This is not documented properly yet</summary>
  </member>
  <member name="M:VRC.SDK3.Image.VRCImageDownloader.ImageDownloader.ImageLoadSettings.SetOutputFormatOverride(System.Nullable)">
    <docURL>???</docURL>
    <incomplete />
    <summary>This is not documented properly yet</summary>
    <param name="outputFormatOverride">???</param>
  </member>
  <member name="M:VRC.SDK3.Image.VRCImageDownloader.ImageDownloader.ImageLoadSettings.SetGenerateMipMaps(System.Boolean)">
    <docURL>???</docURL>
    <incomplete />
    <summary>This is not documented properly yet</summary>
    <param name="enable">???</param>
  </member>
  <member name="M:VRC.SDK3.Image.VRCImageDownloader.ImageDownloader.ImageLoadSettings.GetGenerateMipMaps">
    <docURL>???</docURL>
    <incomplete />
    <summary>This is not documented properly yet</summary>
  </member>
  <member name="M:VRC.SDK3.Image.VRCImageDownloader.ImageDownloader.ImageLoadSettings..ctor">
    <docURL>???</docURL>
    <incomplete />
    <summary>This is not documented properly yet</summary>
  </member>
  <member name="T:VRC.SDK3.Image.VRCImageDownloader">
    <docURL>???</docURL>
    <incomplete />
    <summary>This is not documented properly yet</summary>
  </member>
  <member name="T:VRC.SDK3.Image.VRCImageDownloader.ImageDownloader">
    <docURL>???</docURL>
    <incomplete />
    <summary>This is not documented properly yet</summary>
  </member>
  <member name="T:VRC.SDK3.Image.VRCImageDownloader.ImageDownloader.ImageError">
    <docURL>???</docURL>
    <incomplete />
    <summary>This is not documented properly yet</summary>
  </member>
  <member name="T:VRC.SDK3.Image.VRCImageDownloader.ImageDownloader.ImageFormat">
    <docURL>???</docURL>
    <incomplete />
    <summary>This is not documented properly yet</summary>
  </member>
  <member name="T:VRC.SDK3.Image.VRCImageDownloader.ImageDownloader.ImageInfo">
    <docURL>???</docURL>
    <incomplete />
    <summary>This is not documented properly yet</summary>
  </member>
  <member name="T:VRC.SDK3.Image.VRCImageDownloader.ImageDownloader.ImageResult">
    <docURL>???</docURL>
    <incomplete />
    <summary>This is not documented properly yet</summary>
  </member>
  <member name="T:VRC.SDK3.Image.VRCImageDownloader.ImageDownloader.ImageLoadSettingsFlags">
    <docURL>???</docURL>
    <incomplete />
    <summary>This is not documented properly yet</summary>
  </member>
  <member name="T:VRC.SDK3.Image.VRCImageDownloader.ImageDownloader.ImageLoadSettings">
    <docURL>???</docURL>
    <incomplete />
    <summary>This is not documented properly yet</summary>
  </member>
</members>