<members>
  <member name="P:VRC.SDK3.Editor.Builder.VRCWorldBuilder.Name">
    <docURL>???</docURL>
    <incomplete />
    <summary>This is not documented properly yet</summary>
  </member>
  <member name="M:VRC.SDK3.Editor.Builder.VRCWorldBuilder.ClearEventHandlers">
    <docURL>???</docURL>
    <incomplete />
    <summary>This is not documented properly yet</summary>
  </member>
  <member name="M:VRC.SDK3.Editor.Builder.VRCWorldBuilder.ClearUploadEventHandlers">
    <docURL>???</docURL>
    <incomplete />
    <summary>This is not documented properly yet</summary>
  </member>
  <member name="M:VRC.SDK3.Editor.Builder.VRCWorldBuilder.ExportAvatarBlueprint(UnityEngine.GameObject)">
    <docURL>???</docURL>
    <incomplete />
    <summary>This is not documented properly yet</summary>
  </member>
  <member name="M:VRC.SDK3.Editor.Builder.VRCWorldBuilder.ExportAndUploadAvatarBlueprint(UnityEngine.GameObject)">
    <docURL>???</docURL>
    <incomplete />
    <summary>This is not documented properly yet</summary>
  </member>
  <member name="M:VRC.SDK3.Editor.Builder.VRCWorldBuilder.ExportAndTestAvatarBlueprint(UnityEngine.GameObject)">
    <docURL>???</docURL>
    <incomplete />
    <summary>This is not documented properly yet</summary>
  </member>
  <member name="M:VRC.SDK3.Editor.Builder.VRCWorldBuilder.ExportAndUploadSceneBlueprint">
    <docURL>???</docURL>
    <incomplete />
    <summary>This is not documented properly yet</summary>
  </member>
  <member name="M:VRC.SDK3.Editor.Builder.VRCWorldBuilder.UploadLastExportedSceneBlueprint">
    <docURL>???</docURL>
    <incomplete />
    <summary>This is not documented properly yet</summary>
  </member>
  <member name="M:VRC.SDK3.Editor.Builder.VRCWorldBuilder.RunLastExportedSceneResource">
    <docURL>???</docURL>
    <incomplete />
    <summary>This is not documented properly yet</summary>
  </member>
  <member name="M:VRC.SDK3.Editor.Builder.VRCWorldBuilder.ExportSceneResourceAndRun">
    <docURL>???</docURL>
    <incomplete />
    <summary>This is not documented properly yet</summary>
  </member>
  <member name="M:VRC.SDK3.Editor.Builder.VRCWorldBuilder.ExportSceneResource">
    <docURL>???</docURL>
    <incomplete />
    <summary>This is not documented properly yet</summary>
  </member>
  <member name="M:VRC.SDK3.Editor.Builder.VRCWorldBuilder.ExportSceneToV3">
    <docURL>???</docURL>
    <incomplete />
    <summary>This is not documented properly yet</summary>
  </member>
  <member name="M:VRC.SDK3.Editor.Builder.VRCWorldBuilder.ExportAvatarToV3(UnityEngine.GameObject)">
    <docURL>???</docURL>
    <incomplete />
    <summary>This is not documented properly yet</summary>
  </member>
  <member name="M:VRC.SDK3.Editor.Builder.VRCWorldBuilder..ctor">
    <docURL>???</docURL>
    <incomplete />
    <summary>This is not documented properly yet</summary>
  </member>
  <member name="E:VRC.SDK3.Editor.Builder.VRCWorldBuilder.OnBuildStarted">
    <docURL>???</docURL>
    <incomplete />
    <summary>This is not documented properly yet</summary>
  </member>
  <member name="E:VRC.SDK3.Editor.Builder.VRCWorldBuilder.OnBuildProgress">
    <docURL>???</docURL>
    <incomplete />
    <summary>This is not documented properly yet</summary>
  </member>
  <member name="E:VRC.SDK3.Editor.Builder.VRCWorldBuilder.OnBuildContentProcessed">
    <docURL>???</docURL>
    <incomplete />
    <summary>This is not documented properly yet</summary>
  </member>
  <member name="E:VRC.SDK3.Editor.Builder.VRCWorldBuilder.OnBuildSuccess">
    <docURL>???</docURL>
    <incomplete />
    <summary>This is not documented properly yet</summary>
  </member>
  <member name="E:VRC.SDK3.Editor.Builder.VRCWorldBuilder.OnBuildError">
    <docURL>???</docURL>
    <incomplete />
    <summary>This is not documented properly yet</summary>
  </member>
  <member name="E:VRC.SDK3.Editor.Builder.VRCWorldBuilder.OnContentPreUpload">
    <docURL>???</docURL>
    <incomplete />
    <summary>This is not documented properly yet</summary>
  </member>
  <member name="T:VRC.SDK3.Editor.Builder.VRCWorldBuilder">
    <docURL>???</docURL>
    <incomplete />
    <summary>This is not documented properly yet</summary>
  </member>
</members>